{
  "swagger": "2.0",
  "info": {
    "version": "20180322T125214Z",
    "title": "ACCLAKE-api",
    "x-jentic-source-url": "https://api.swaggerhub.com/apis/Acce28/acclake-api/20180322T125214Z/swagger.json"
  },
  "host": "s0x2yverr1.execute-api.us-east-1.amazonaws.com",
  "basePath": "/sandbox",
  "schemes": [
    "https"
  ],
  "paths": {
    "/indireto": {
      "options": {
        "consumes": [
          "application/json"
        ],
        "produces": [
          "application/json"
        ],
        "responses": {
          "200": {
            "description": "200 response",
            "schema": {
              "$ref": "#/definitions/Empty"
            },
            "headers": {
              "Access-Control-Allow-Origin": {
                "type": "string"
              },
              "Access-Control-Allow-Methods": {
                "type": "string"
              },
              "Access-Control-Allow-Headers": {
                "type": "string"
              }
            }
          }
        }
      }
    },
    "/indireto/extract": {
      "options": {
        "consumes": [
          "application/json"
        ],
        "produces": [
          "application/json"
        ],
        "responses": {
          "200": {
            "description": "200 response",
            "schema": {
              "$ref": "#/definitions/Empty"
            },
            "headers": {
              "Access-Control-Allow-Origin": {
                "type": "string"
              },
              "Access-Control-Allow-Methods": {
                "type": "string"
              },
              "Access-Control-Allow-Headers": {
                "type": "string"
              }
            }
          }
        }
      }
    },
    "/indireto/extract/create": {
      "post": {
        "consumes": [
          "application/json"
        ],
        "produces": [
          "application/json"
        ],
        "responses": {
          "200": {
            "description": "200 response",
            "schema": {
              "$ref": "#/definitions/Empty"
            }
          }
        },
        "security": [
          {
            "ACCLAKE-AcceraKey-Authorizer": []
          }
        ]
      },
      "options": {
        "consumes": [
          "application/json"
        ],
        "produces": [
          "application/json"
        ],
        "responses": {
          "200": {
            "description": "200 response",
            "schema": {
              "$ref": "#/definitions/Empty"
            },
            "headers": {
              "Access-Control-Allow-Origin": {
                "type": "string"
              },
              "Access-Control-Allow-Methods": {
                "type": "string"
              },
              "Access-Control-Allow-Headers": {
                "type": "string"
              }
            }
          }
        }
      }
    },
    "/indireto/extract/status": {
      "post": {
        "consumes": [
          "application/json"
        ],
        "produces": [
          "application/json"
        ],
        "responses": {
          "200": {
            "description": "200 response",
            "schema": {
              "$ref": "#/definitions/Empty"
            }
          }
        },
        "security": [
          {
            "ACCLAKE-AcceraKey-Authorizer": []
          }
        ]
      },
      "options": {
        "consumes": [
          "application/json"
        ],
        "produces": [
          "application/json"
        ],
        "responses": {
          "200": {
            "description": "200 response",
            "schema": {
              "$ref": "#/definitions/Empty"
            },
            "headers": {
              "Access-Control-Allow-Origin": {
                "type": "string"
              },
              "Access-Control-Allow-Methods": {
                "type": "string"
              },
              "Access-Control-Allow-Headers": {
                "type": "string"
              }
            }
          }
        }
      }
    }
  },
  "securityDefinitions": {
    "ACCLAKE-AcceraKey-Authorizer": {
      "type": "apiKey",
      "name": "Accera-Key",
      "in": "header",
      "x-amazon-apigateway-authtype": "custom"
    }
  },
  "definitions": {
    "Empty": {
      "type": "object",
      "title": "Empty Schema"
    }
  }
}