{
  "aid": "messagebird.com:messagebird-faq-api-version not set",
  "name": "FAQ",
  "type": "Index",
  "description": "messagebird.com/messagebird-faq-api version version not set",
  "url": "https://raw.githubusercontent.com/jentic/jentic-public-apis/refs/heads/main/apis/openapi/messagebird.com/messagebird-faq-api/version not set/apis.json",
  "tags": [
    "messagebird.com",
    "messagebird-faq-api"
  ],
  "created": "2026-04-01",
  "modified": "2026-04-01",
  "specificationVersion": "0.19",
  "access": "3rd-Party",
  "maintainers": [
    {
      "FN": "Jentic",
      "X-github": "jentic",
      "url": "https://github.com/jentic"
    }
  ],
  "apis": [
    {
      "aid": "messagebird.com:messagebird-faq-api-version not set",
      "name": "FAQ",
      "description": "messagebird.com/messagebird-faq-api version version not set",
      "image": "",
      "baseURL": "https://faq.messagebird.com/",
      "humanURL": "https://developers.messagebird.com/api",
      "version": "version not set",
      "tags": [
        "messagebird.com",
        "messagebird-faq-api"
      ],
      "properties": [
        {
          "type": "OpenAPI",
          "name": "OpenAPI definition",
          "url": "https://raw.githubusercontent.com/jentic/jentic-public-apis/refs/heads/main/apis/openapi/messagebird.com/messagebird-faq-api/version not set/openapi.json",
          "mediaType": "application/openapi+json"
        },
        {
          "type": "GitHubRepo",
          "url": "https://github.com/jentic/jentic-public-apis/tree/main/apis/openapi/messagebird.com/messagebird-faq-api/version not set"
        }
      ]
    }
  ]
}